[
  { "old": "06010601", "new": "06090201", "name_km": "ពោន" },
  { "old": "06010602", "new": "06090202", "name_km": "ច្រនាង" },
  { "old": "06010603", "new": "06090203", "name_km": "ត្រពាំងវែង" },
  { "old": "06010604", "new": "06090204", "name_km": "ថ្លា" },
  { "old": "06010605", "new": "06090205", "name_km": "ចាន់" },
  { "old": "06010606", "new": "06090206", "name_km": "ស្រះបន្ទាយ" },
  { "old": "06010607", "new": "06090207", "name_km": "សៀមរាង" },
  { "old": "06010608", "new": "06090208", "name_km": "អង្គរជា" },
  { "old": "06010609", "new": "06090209", "name_km": "កន្ធំ" },
  { "old": "06010610", "new": "06090210", "name_km": "ត្រពាំងខ្លង" },
  { "old": "06010611", "new": "06090211", "name_km": "ប្រាំងសំរោង" },
  { "old": "06010612", "new": "06090212", "name_km": "អូរំចេក" },
  { "old": "06010613", "new": "06090213", "name_km": "ប៉ាង" },
  { "old": "06010901", "new": "06090301", "name_km": "ទួលទំពូង" },
  { "old": "06010902", "new": "06090302", "name_km": "បុស្សស្បែង" },
  { "old": "06010903", "new": "06090303", "name_km": "ជាប" },
  { "old": "06010904", "new": "06090304", "name_km": "ត្រណាល" },
  { "old": "06010905", "new": "06090305", "name_km": "ថ្មអណ្ដែត" },
  { "old": "06010906", "new": "06090306", "name_km": "ត្រពាំងឈូក" },
  { "old": "06010907", "new": "06090307", "name_km": "សេរីចំប៉ា" },
  { "old": "06010908", "new": "06090308", "name_km": "ហាន់ទ្វារ" },
  { "old": "06010909", "new": "06090309", "name_km": "ត្រពាំងច្រនៀង" },
  { "old": "06011201", "new": "06090801", "name_km": "ជីវភាព" },
  { "old": "06011202", "new": "06090802", "name_km": "បែកចាន" },
  { "old": "06011203", "new": "06090803", "name_km": "ដំរីស្លាប់" },
  { "old": "06011204", "new": "06090804", "name_km": "អណ្ដូងពោធិ៍" },
  { "old": "06011205", "new": "06090805", "name_km": "វាលតូច" },
  { "old": "06011206", "new": "06090806", "name_km": "គុហ៍បារែង" },
  { "old": "06011207", "new": "06090807", "name_km": "គ្រើល" },
  { "old": "06011301", "new": "06090101", "name_km": "តាព្រៃ" },
  { "old": "06011302", "new": "06090102", "name_km": "អូររាំង" },
  { "old": "06011303", "new": "06090103", "name_km": "ពង្រ" },
  { "old": "06011304", "new": "06090104", "name_km": "អមទង" },
  { "old": "06011305", "new": "06090105", "name_km": "ត្រដក់ពង" },
  { "old": "06011306", "new": "06090106", "name_km": "ស្រះសំបួរ" },
  { "old": "06011307", "new": "06090107", "name_km": "ថ្នល់កែង" },
  { "old": "06011401", "new": "06090501", "name_km": "តាំងគោក" },
  { "old": "06011402", "new": "06090502", "name_km": "រស្មីរំដោះ" },
  { "old": "06011403", "new": "06090503", "name_km": "សង្គមមានជ័យ" },
  { "old": "06011404", "new": "06090504", "name_km": "តាម៉ី" },
  { "old": "06011405", "new": "06090505", "name_km": "ថ្លា" },
  { "old": "06011406", "new": "06090506", "name_km": "ខ្លុយកើត" },
  { "old": "06011407", "new": "06090507", "name_km": "ខ្លុយលិច" },
  { "old": "06011408", "new": "06090508", "name_km": "សៀមរាយ" },
  { "old": "06011409", "new": "06090509", "name_km": "សូយោង" },
  { "old": "06011410", "new": "06090510", "name_km": "ខ្ញោម" },
  { "old": "06011411", "new": "06090511", "name_km": "កាតាយ" },
  { "old": "06011501", "new": "06090601", "name_km": "សេរីសាមគ្គីខាងត្បូង" },
  { "old": "06011502", "new": "06090602", "name_km": "សេរីសាមគ្គីខាងជើង" },
  { "old": "06011503", "new": "06090603", "name_km": "ដំរីស្លាប់" },
  { "old": "06011504", "new": "06090604", "name_km": "គគរ" },
  { "old": "06011505", "new": "06090605", "name_km": "អ្នកវាំង" },
  { "old": "06011506", "new": "06090606", "name_km": "ទួលអំពិល" },
  { "old": "06011507", "new": "06090607", "name_km": "សេរីសាមគ្កីកណ្ដាល" },
  { "old": "06011508", "new": "06090608", "name_km": "ស្នួល" },
  { "old": "06011509", "new": "06090609", "name_km": "គោកអណ្ដែត" },
  { "old": "06011510", "new": "06090610", "name_km": "ទួលពភ្លា" },
  { "old": "06011511", "new": "06090611", "name_km": "បុស្សល្វា" },
  { "old": "06011512", "new": "06090612", "name_km": "ទោង" },
  { "old": "06011513", "new": "06090613", "name_km": "ដំណាក់" },
  { "old": "06011514", "new": "06090614", "name_km": "ឧទុម្ពរ" },
  { "old": "06011515", "new": "06090615", "name_km": "គោកត្របែក" },
  { "old": "06011601", "new": "06090701", "name_km": "ប្រតោង" },
  { "old": "06011602", "new": "06090702", "name_km": "ស្វាយភ្លើង" },
  { "old": "06011603", "new": "06090703", "name_km": "ខ្នាយទង" },
  { "old": "06011604", "new": "06090704", "name_km": "ក្រូច" },
  { "old": "06011605", "new": "06090705", "name_km": "ត្រពាំងសង្កែ" },
  { "old": "06011606", "new": "06090706", "name_km": "ប៉ប្រក" },
  { "old": "06011607", "new": "06090707", "name_km": "ឫស្សីល័រ" },
  { "old": "06011801", "new": "06090401", "name_km": "គីរីអណ្ដែត" },
  { "old": "06011802", "new": "06090402", "name_km": "រំចេក" },
  { "old": "06011803", "new": "06090403", "name_km": "ព្នៅ" },
  { "old": "06011804", "new": "06090404", "name_km": "ស្វាយម្សៅ" },
  { "old": "06011805", "new": "06090405", "name_km": "ឈូក" },
  { "old": "06011806", "new": "06090406", "name_km": "ទ្រៀល" },
  { "old": "06011807", "new": "06090407", "name_km": "ទន្លេវល្លិ" },
  { "old": "06011808", "new": "06090408", "name_km": "សាលាឃុំ" },
  { "old": "06011809", "new": "06090409", "name_km": "កំញ៉ាត" },
  { "old": "06011810", "new": "06090410", "name_km": "ត្នោត" },
  { "old": "06011811", "new": "06090411", "name_km": "ថ្មី" },
  { "old": "06011812", "new": "06090412", "name_km": "រពាក់ពេន" },
  { "old": "06011813", "new": "06090413", "name_km": "អង្គរនាង" },
  { "old": "06011814", "new": "06090414", "name_km": "នាងល្អ" },
  { "old": "06011815", "new": "06090415", "name_km": "ប្រខ្នាយ" },
  { "old": "06011816", "new": "06090416", "name_km": "កំចាយមារ" },
  { "old": "06011817", "new": "06090417", "name_km": "ដារ" },
  { "old": "06011818", "new": "06090418", "name_km": "ក្ដីតាចិន" },
  { "old": "06011819", "new": "06090419", "name_km": "វាលអំពិល" },
  { "old": "06011820", "new": "06090420", "name_km": "ព្រៃវែង" },
  { "old": "06011821", "new": "06090421", "name_km": "ថ្នល់" },
  { "old": "06011822", "new": "06090422", "name_km": "ប្រិច" },
  { "old": "08100201", "new": "08110801", "name_km": "ក្បាលកោះ" },
  { "old": "08100202", "new": "08110802", "name_km": "កណ្ដាលកោះ" },
  { "old": "08100203", "new": "08110803", "name_km": "ស្វាយពងអង្ក្រង" },
  { "old": "08100204", "new": "08110804", "name_km": "ចុងកោះ" },
  { "old": "08100901", "new": "08111001", "name_km": "កោះគរ" },
  { "old": "08100902", "new": "08111002", "name_km": "ព្រែកថី" },
  { "old": "08100903", "new": "08111003", "name_km": "ព្រែកសំរោង" },
  { "old": "08100904", "new": "08111004", "name_km": "ព្រែកខ្សេវ" },
  { "old": "08100905", "new": "08111005", "name_km": "ទួលក្រសាំង" },
  { "old": "08100906", "new": "08111006", "name_km": "កោះរំដួល" },
  { "old": "08100907", "new": "08111007", "name_km": "ព្រែកឡុង" },
  { "old": "08101101", "new": "08110901", "name_km": "ព្រែកតាព្រីង" },
  { "old": "08101102", "new": "08110902", "name_km": "សិត្បូ" },
  { "old": "08101103", "new": "08110903", "name_km": "កំពង់ព្រីង" },
  { "old": "08101104", "new": "08110904", "name_km": "ព្រែកត្រែង" },
  { "old": "08101301", "new": "08110701", "name_km": "លេខ១" },
  { "old": "08101302", "new": "08110702", "name_km": "លេខ២" },
  { "old": "08101303", "new": "08110703", "name_km": "លេខ៣" },
  { "old": "08101304", "new": "08110704", "name_km": "លេខ៤" },
  { "old": "08101305", "new": "08110705", "name_km": "លេខ៥" },
  { "old": "08110706", "new": "08101306", "name_km": "លេខ១ ក" },
  { "old": "12010201", "new": "12130101", "name_km": "ភូមិ ១" },
  { "old": "12010202", "new": "12130102", "name_km": "ភូមិ ២" },
  { "old": "12010203", "new": "12130103", "name_km": "ភូមិ ៣" },
  { "old": "12010204", "new": "12130104", "name_km": "ភូមិ ៤" },
  { "old": "12010205", "new": "12130105", "name_km": "ភូមិ ៥" },
  { "old": "12010206", "new": "12130106", "name_km": "ភូមិ ៦" },
  { "old": "12010207", "new": "12130107", "name_km": "ភូមិ ៧" },
  { "old": "12010208", "new": "12130108", "name_km": "ភូមិ ៨" },
  { "old": "12010209", "new": "12130109", "name_km": "ភូមិ ៩" },
  { "old": "12010301", "new": "12130201", "name_km": "ភូមិ ១" },
  { "old": "12010302", "new": "12130202", "name_km": "ភូមិ ២" },
  { "old": "12010303", "new": "12130203", "name_km": "ភូមិ ៣" },
  { "old": "12010304", "new": "12130204", "name_km": "ភូមិ ៤" },
  { "old": "12010305", "new": "12130205", "name_km": "ភូមិ ៥" },
  { "old": "12010306", "new": "12130206", "name_km": "ភូមិ ៦" },
  { "old": "12010307", "new": "12130207", "name_km": "ភូមិ ៧" },
  { "old": "12010308", "new": "12130208", "name_km": "ភូមិ ៨" },
  { "old": "12010309", "new": "12130209", "name_km": "ភូមិ ៩" },
  { "old": "12010401", "new": "12130301", "name_km": "ភូមិ ១" },
  { "old": "12010402", "new": "12130302", "name_km": "ភូមិ ២" },
  { "old": "12010403", "new": "12130303", "name_km": "ភូមិ ៣" },
  { "old": "12010404", "new": "12130304", "name_km": "ភូមិ ៤" },
  { "old": "12010405", "new": "12130305", "name_km": "ភូមិ ៥" },
  { "old": "12010406", "new": "12130306", "name_km": "ភូមិ ៦" },
  { "old": "12010407", "new": "12130307", "name_km": "ភូមិ ៧" },
  { "old": "12010408", "new": "12130308", "name_km": "ភូមិ ៨" },
  { "old": "12010409", "new": "12130309", "name_km": "ភូមិ ៩" },
  { "old": "12010501", "new": "12130401", "name_km": "ភូមិ ១" },
  { "old": "12010502", "new": "12130402", "name_km": "ភូមិ ២" },
  { "old": "12010503", "new": "12130403", "name_km": "ភូមិ ៣" },
  { "old": "12010504", "new": "12130404", "name_km": "ភូមិ ៤" },
  { "old": "12010505", "new": "12130405", "name_km": "ភូមិ ៥" },
  { "old": "12010601", "new": "12130601", "name_km": "ភូមិ ១" },
  { "old": "12010602", "new": "12130602", "name_km": "ភូមិ ២" },
  { "old": "12010603", "new": "12130603", "name_km": "ភូមិ ៣" },
  { "old": "12010604", "new": "12130604", "name_km": "ភូមិ ៤" },
  { "old": "12010605", "new": "12130605", "name_km": "ភូមិ ៥" },
  { "old": "12010606", "new": "12130606", "name_km": "ភូមិ ៦" },
  { "old": "12010607", "new": "12130607", "name_km": "ភូមិ ៧" },
  { "old": "12010801", "new": "12130501", "name_km": "ភូមិ ១" },
  { "old": "12010802", "new": "12130502", "name_km": "ភូមិ ២" },
  { "old": "12010803", "new": "12130503", "name_km": "ភូមិ ៣" },
  { "old": "12010804", "new": "12130504", "name_km": "ភូមិ ៤" },
  { "old": "12010805", "new": "12130505", "name_km": "ភូមិ ៥" },
  { "old": "12051301", "new": "12140701", "name_km": "ប្រទះឡាង" },
  { "old": "12051302", "new": "12140702", "name_km": "ភា" },
  { "old": "12051303", "new": "12140703", "name_km": "អង្គ" },
  { "old": "12051304", "new": "12140704", "name_km": "តាំងរនាម" },
  { "old": "12051305", "new": "12140705", "name_km": "គោកខ្សាច់" },
  { "old": "12051306", "new": "12140706", "name_km": "គោកមាស" },
  { "old": "12090301", "new": "12140501", "name_km": "ទួលកី" },
  { "old": "12090302", "new": "12140502", "name_km": "កប់ភ្លុក" },
  { "old": "12090303", "new": "12140503", "name_km": "ព្រៃរងៀង" },
  { "old": "12090304", "new": "12140504", "name_km": "ត្រាញ់តាបាញ់" },
  { "old": "12090305", "new": "12140505", "name_km": "ភ្លើងឆេះរទេះលិច" },
  { "old": "12090306", "new": "12140506", "name_km": "ភ្លើងឆេះរទេះកើត" },
  { "old": "12090307", "new": "12140507", "name_km": "គោកខ្សាច់" },
  { "old": "12090308", "new": "12140508", "name_km": "ព្រៃកី" },
  { "old": "12090801", "new": "12140601", "name_km": "ត្មាតពង" },
  { "old": "12090802", "new": "12140602", "name_km": "ព្រៃរមាសទី២" },
  { "old": "12090803", "new": "12140603", "name_km": "ព្រៃរមាសទី១" },
  { "old": "12090804", "new": "12140604", "name_km": "តាជេត" },
  { "old": "12090805", "new": "12140605", "name_km": "បឹងធំទី១" },
  { "old": "12090806", "new": "12140606", "name_km": "បឹងធំទី២" },
  { "old": "12090807", "new": "12140607", "name_km": "បឹងធំទី៣" },
  { "old": "12090808", "new": "12140608", "name_km": "ដូនកុក" },
  { "old": "12090809", "new": "12140609", "name_km": "ខ្ចៅ" },
  { "old": "12090810", "new": "12140610", "name_km": "ក្ងោក" },
  { "old": "12090811", "new": "12140611", "name_km": "ទួលស្វាយ" },
  { "old": "12090812", "new": "12140612", "name_km": "ត្រពាំងក្រសាំង" },
  { "old": "12090813", "new": "12140613", "name_km": "ចំបក់ពណ្ណរាយ" },
  { "old": "12090814", "new": "12140614", "name_km": "ត្រពាំងត្រប់" },
  { "old": "12090815", "new": "12140615", "name_km": "អន្លុងស្វាយ" },
  { "old": "12090816", "new": "12140616", "name_km": "ព្រៃតាកែ" },
  { "old": "12090901", "new": "12140101", "name_km": "ផ្សារកំបូល" },
  { "old": "12090902", "new": "12140102", "name_km": "តាកេរិ៍្ដ" },
  { "old": "12090903", "new": "12140103", "name_km": "ត្រពាំងទួល" },
  { "old": "12090904", "new": "12140104", "name_km": "កំបូល" },
  { "old": "12090905", "new": "12140105", "name_km": "ទួលតាឡាត់" },
  { "old": "12090906", "new": "12140106", "name_km": "តាភេម" },
  { "old": "12090907", "new": "12140107", "name_km": "ព្រៃកុដិ" },
  { "old": "12090908", "new": "12140108", "name_km": "តាសេក" },
  { "old": "12090909", "new": "12140109", "name_km": "ទួលសាម៉" },
  { "old": "12090910", "new": "12140110", "name_km": "តានួន" },
  { "old": "12090911", "new": "12140111", "name_km": "កប់អំបិល" },
  { "old": "12090912", "new": "12140112", "name_km": "ស្នួលខ្ពស់" },
  { "old": "12090913", "new": "12140113", "name_km": "អំពិល" },
  { "old": "12090914", "new": "12140114", "name_km": "ត្រិប" },
  { "old": "12090915", "new": "12140115", "name_km": "សាឡូង" },
  { "old": "12090916", "new": "12140116", "name_km": "ជំទាវម៉ៅ" },
  { "old": "12090917", "new": "12140117", "name_km": "អង្គបឹងចក" },
  { "old": "12090918", "new": "12140118", "name_km": "លិចវត្ដ" },
  { "old": "12091002", "new": "12140201", "name_km": "ថ្មដា" },
  { "old": "12091003", "new": "12140202", "name_km": "ត្រពាំងគល់" },
  { "old": "12091004", "new": "12140203", "name_km": "ស្ងួនពេជ្រ" },
  { "old": "12091005", "new": "12140204", "name_km": "កន្ទោកត្បូង" },
  { "old": "12091006", "new": "12140205", "name_km": "គល់" },
  { "old": "12091007", "new": "12140206", "name_km": "អង្គត្រគៀត" },
  { "old": "12091008", "new": "12140207", "name_km": "កន្ទោកជើង" },
  { "old": "12091009", "new": "12140208", "name_km": "ត្រពាំងឈូក" },
  { "old": "12091010", "new": "12140209", "name_km": "ស្រែក្នុង" },
  { "old": "12091012", "new": "12140210", "name_km": "ព្រៃបឹង" },
  { "old": "12091013", "new": "12140211", "name_km": "កំរៀង" },
  { "old": "12091015", "new": "12140212", "name_km": "ដំបូកខ្ពស់" },
  { "old": "12091017", "new": "12140213", "name_km": "ត្រាំស្លឹក" },
  { "old": "12091101", "new": "12140301", "name_km": "ព្រៃតាប៉ុក" },
  { "old": "12091102", "new": "12140302", "name_km": "ត្រពាំងកក់" },
  { "old": "12091103", "new": "12140303", "name_km": "អង្គស្លែង" },
  { "old": "12091104", "new": "12140304", "name_km": "ដូនរ័ត្ន" },
  { "old": "12091105", "new": "12140305", "name_km": "ត្រពាំងអារ័ក្ស" },
  { "old": "12091106", "new": "12140306", "name_km": "ត្រពាំងពោធិ៍" },
  { "old": "12091107", "new": "12140307", "name_km": "បឹងគ្រើល" },
  { "old": "12091108", "new": "12140308", "name_km": "ជ័យជំនះ" },
  { "old": "12091109", "new": "12140309", "name_km": "បឹងកំបោរ" },
  { "old": "12091110", "new": "12140310", "name_km": "ត្បែងមានជ័យ" },
  { "old": "12091111", "new": "12140311", "name_km": "ត្រង់នំ" },
  { "old": "12091112", "new": "12140312", "name_km": "ពង្រ" },
  { "old": "12091113", "new": "12140313", "name_km": "ថ្ម" },
  { "old": "12091114", "new": "12140314", "name_km": "សាមគ្គីប្រយុទ្ធ" },
  { "old": "12091301", "new": "12140401", "name_km": "សាក់ប្រយុទ្ធ" },
  { "old": "12091302", "new": "12140402", "name_km": "អង្គរជ័យ" },
  { "old": "12091303", "new": "12140403", "name_km": "ស្រែអំពិល" },
  { "old": "12091304", "new": "12140404", "name_km": "តាអិន" },
  { "old": "12091305", "new": "12140405", "name_km": "កុលក្រស្នារ" },
  { "old": "12091306", "new": "12140406", "name_km": "ប្រាសាទ" },
  { "old": "12091307", "new": "12140407", "name_km": "ស្វាយ" },
  { "old": "12091308", "new": "12140408", "name_km": "ស្នោរកើត" },
  { "old": "12091309", "new": "12140409", "name_km": "តាពូង" },
  { "old": "12091310", "new": "12140410", "name_km": "ផ្លាំង" },
  { "old": "12091311", "new": "12140411", "name_km": "ស្នោរលិច" },
  { "old": "12091312", "new": "12140412", "name_km": "ពង្រ" },
  { "old": "12091313", "new": "12140413", "name_km": "ព្រៃរឹង" },
  { "old": "12091314", "new": "12140414", "name_km": "រំដួលជើង" },
  { "old": "12091315", "new": "12140415", "name_km": "រំដួលត្បូង" },
  { "old": "12091316", "new": "12140416", "name_km": "ទួលលៀប" },
  { "old": "12091317", "new": "12140417", "name_km": "ព្រៃក្រាយ" },
  { "old": "12091318", "new": "12140418", "name_km": "ព្រៃឈូក" },
  { "old": "14110501", "new": "14100401", "name_km": "កុកត្រុំ ក" },
  { "old": "14110502", "new": "14100402", "name_km": "កុកត្រុំ ខ" },
  { "old": "14110503", "new": "14100403", "name_km": "ខ្នយ" },
  { "old": "14110504", "new": "14100404", "name_km": "ភ្លយ" },
  { "old": "14110505", "new": "14100405", "name_km": "ស្គដាច" },
  { "old": "14110506", "new": "14100406", "name_km": "ត្នោតទ្រេត" },
  { "old": "14110507", "new": "14100407", "name_km": "តាកោ" },
  { "old": "14110508", "new": "14100408", "name_km": "ភគ្គនេស្ស" },
  { "old": "15010901", "new": "15070101", "name_km": "គោករំល" },
  { "old": "15010902", "new": "15070102", "name_km": "ទួលទទឹង" },
  { "old": "15010903", "new": "15070103", "name_km": "ទួលថ្ម" },
  { "old": "15010904", "new": "15070104", "name_km": "បួច្រេស" },
  { "old": "15010905", "new": "15070105", "name_km": "ព្រៃរោង" },
  { "old": "15010906", "new": "15070106", "name_km": "តាលោ" },
  { "old": "15010907", "new": "15070107", "name_km": "ថ្មី" },
  { "old": "15010908", "new": "15070108", "name_km": "ទួលជ្រាវ" },
  { "old": "15010909", "new": "15070109", "name_km": "ព្រៃតោ" },
  { "old": "15010910", "new": "15070110", "name_km": "បឹងកក់" },
  { "old": "15010911", "new": "15070111", "name_km": "ព្រៃវាំង" },
  { "old": "15010912", "new": "15070112", "name_km": "សិរីគន្ធា" },
  { "old": "15010913", "new": "15070113", "name_km": "ត្រយ៉ងស" },
  { "old": "15010914", "new": "15070114", "name_km": "ឆ្នាល់មាន់" },
  { "old": "15010915", "new": "15070115", "name_km": "ព្រៃកន្ទួត" },
  { "old": "15010916", "new": "15070116", "name_km": "តាំងគោក" },
  { "old": "15010917", "new": "15070117", "name_km": "បោសគរ" },
  { "old": "15010918", "new": "15070118", "name_km": "ប្រហាល" },
  { "old": "15010919", "new": "15070119", "name_km": "រហាលទិល" },
  { "old": "15010920", "new": "15070120", "name_km": "សំសាន្ត" },
  { "old": "15070121", "new": "15010302", "name_km": "កោះស្វាយ" },
  { "old": "15010312", "new": "15070122", "name_km": "កោះវត្ដ" },
  { "old": "15040301", "new": "15070201", "name_km": "កោះស្វាយ" },
  { "old": "15040302", "new": "15070202", "name_km": "តាសាស់" },
  { "old": "15040303", "new": "15070203", "name_km": "ក្រញាំ" },
  { "old": "15040304", "new": "15070204", "name_km": "ព្រៃកន្លង់" },
  { "old": "15040305", "new": "15070205", "name_km": "ថ្លុកដង្កោ" },
  { "old": "15040306", "new": "15070206", "name_km": "បត់រំដួល" },
  { "old": "15040307", "new": "15070207", "name_km": "កណ្ដាល" },
  { "old": "15040308", "new": "15070208", "name_km": "ផ្ទះរុង" },
  { "old": "15040309", "new": "15070209", "name_km": "ដំណាក់កន្សែង" },
  { "old": "15040310", "new": "15070210", "name_km": "ស្ដុកខ្ទុំ" },
  { "old": "15040311", "new": "15070211", "name_km": "ព្រហស្បតិ៍ក្បាល" },
  { "old": "15040312", "new": "15070212", "name_km": "ជង្រុក" },
  { "old": "15040313", "new": "15070213", "name_km": "ជ្រៃក្រឹម" },
  { "old": "18010502", "new": "18050101", "name_km": "ដើមថ្កូវ" },
  { "old": "18010503", "new": "18050102", "name_km": "ព្រែកស្វាយ" },
  { "old": "18010601", "new": "18050201", "name_km": "កោះតូច" },
  { "old": "18010602", "new": "18050202", "name_km": "កោះរ៉ុងសន្លឹម" },
  { "old": "18050101", "new": "18010502", "name_km": "ដើមថ្កូវ" },
  { "old": "18050102", "new": "18010503", "name_km": "ព្រែកស្វាយ" },
  { "old": "18050201", "new": "18010601", "name_km": "កោះតូច" },
  { "old": "18050202", "new": "18010602", "name_km": "កោះរ៉ុងសន្លឹម" },
  { "old": "19050401", "new": "19060201", "name_km": "កោះស្នែង" },
  { "old": "19050402", "new": "19060202", "name_km": "កោះស្រឡៅ" },
  { "old": "19050403", "new": "19060203", "name_km": "កោះកី" },
  { "old": "19050404", "new": "19060204", "name_km": "ជាំធំ" },
  { "old": "19050701", "new": "19060101", "name_km": "កោះព្នៅ" },
  { "old": "19050702", "new": "19060102", "name_km": "អូរស្វាយ" },
  { "old": "19050703", "new": "19060103", "name_km": "អូររុន" },
  { "old": "19050704", "new": "19060104", "name_km": "វើនសៀន" },
  { "old": "19050705", "new": "19060105", "name_km": "កោះហិប" },
  { "old": "19030407", "new": "19060106", "name_km": "ណាអូង" },
  { "old": "19050801", "new": "19060301", "name_km": "លើ" },
  { "old": "19050802", "new": "19060302", "name_km": "កណ្ដាល" },
  { "old": "19050803", "new": "19060303", "name_km": "កោះឈើទាលតូច" },
  { "old": "19050804", "new": "19060304", "name_km": "កោះឈើទាលធំ" },
  { "old": "19050805", "new": "19060305", "name_km": "កោះល្ង" },
  { "old": "19050806", "new": "19060306", "name_km": "ក្រឡាពាស" },
  { "old": "19050807", "new": "19060307", "name_km": "ក្រោម" },
  { "old": "19050808", "new": "19060308", "name_km": "អន្លង់ស្វាយ" }
]
